mero/__init__.py
mero/bytecode.py
mero/cipher.py
mero/core.py
mero/executor.py
mero/hash.py
mero/keymaster.py
mero/megabytes.py
mero/obfuscator.py
mero/platform.py
mero/protector.py
mero/quantum_cipher.py
mero/stream.py
mero-2.0.0.dist-info/LICENSE
mero-2.0.0.dist-info/METADATA
mero-2.0.0.dist-info/WHEEL
mero-2.0.0.dist-info/top_level.txt
mero-2.0.0.dist-info/RECORD
