Metadata-Version: 2.1
Name: mero
Version: 2.0.0
Summary: Professional-grade Python encryption library with custom bytecode implementation
Author: Mero Security
Author-email: security@mero.dev
Project-URL: Documentation, https://mero-crypto.readthedocs.io/
Project-URL: Source, https://github.com/mero-security/mero
Project-URL: Tracker, https://github.com/mero-security/mero/issues
Keywords: encryption cryptography security bytecode obfuscation
Classifier: Development Status :: 5 - Production/Stable
Classifier: Intended Audience :: Developers
Classifier: License :: OSI Approved :: MIT License
Classifier: Programming Language :: Python :: 3
Classifier: Programming Language :: Python :: 3.6
Classifier: Programming Language :: Python :: 3.7
Classifier: Programming Language :: Python :: 3.8
Classifier: Programming Language :: Python :: 3.9
Classifier: Programming Language :: Python :: 3.10
Classifier: Programming Language :: Python :: 3.11
Classifier: Topic :: Security :: Cryptography
Classifier: Topic :: Software Development :: Libraries :: Python Modules
Requires-Python: >=3.6
License-File: LICENSE
